synthesized_insight/__init__.py
synthesized_insight/check.py
synthesized_insight/version.py
synthesized_insight/metrics/__init__.py
synthesized_insight/metrics/base.py
synthesized_insight/metrics/confidence_interval.py
synthesized_insight/metrics/metrics.py
synthesized_insight/metrics/metrics_usage.py
synthesized_insight/metrics/modelling_metrics.py
synthesized_insight/metrics/privacy.py
synthesized_insight/metrics/privacy_cap_scorer.py
synthesized_insight/metrics/statistical_tests.py
synthesized_insight/metrics/utils.py
synthesized_insight/modelling/__init__.py
synthesized_insight/modelling/preprocessor.py
synthesized_insight/modelling/utility.py
synthesized_insight-0.7.dist-info/LICENSE.md
synthesized_insight-0.7.dist-info/METADATA
synthesized_insight-0.7.dist-info/WHEEL
synthesized_insight-0.7.dist-info/top_level.txt
synthesized_insight-0.7.dist-info/RECORD
