Metadata-Version: 2.1
Name: synthesized-insight
Version: 0.7
Summary: Synthesized data insights and evaluation framework.
Home-page: https://synthesized.io
Author-email: "Synthesized Ltd." <sdk-team@synthesized.io>
License: BSD 3-Clause License        
Project-URL: homepage, https://synthesized.io
Project-URL: documentation, https://docs.synthesized.io/
Project-URL: repository, https://github.com/synthesized-io/synthesized-insight
Keywords: metrics,data,evaluation
Platform: MacOS
Platform: Windows
Platform: Linux
Classifier: Development Status :: 5 - Production/Stable
Classifier: License :: OSI Approved :: BSD License
Classifier: Intended Audience :: Developers
Classifier: Intended Audience :: Science/Research
Classifier: Intended Audience :: Financial and Insurance Industry
Classifier: Intended Audience :: Information Technology
Classifier: Intended Audience :: Healthcare Industry
Classifier: Operating System :: MacOS
Classifier: Operating System :: Microsoft :: Windows
Classifier: Operating System :: POSIX
Classifier: Operating System :: Unix
Classifier: Programming Language :: Python :: 3
Classifier: Programming Language :: Python :: 3 :: Only
Classifier: Programming Language :: Python :: 3.7
Classifier: Programming Language :: Python :: 3.8
Classifier: Programming Language :: Python :: 3.9
Classifier: Topic :: Scientific/Engineering
Requires-Python: >=3.7
License-File: LICENSE.md
Requires-Dist: numpy (>=1.18)
Requires-Dist: pandas (>=1.2)
Requires-Dist: scikit-learn (>=0.23)
Requires-Dist: scipy (>=1.5)
Provides-Extra: dev
Requires-Dist: pre-commit ; extra == 'dev'
Requires-Dist: black ; extra == 'dev'
Requires-Dist: mypy ; extra == 'dev'
Requires-Dist: pylint ; extra == 'dev'
Provides-Extra: doc
Requires-Dist: sphinx (==4.5.0) ; extra == 'doc'
Requires-Dist: pydata-sphinx-theme (==0.8.1) ; extra == 'doc'
Requires-Dist: sphinx-panels (==0.6.0) ; extra == 'doc'
Requires-Dist: sphinx-autodoc-typehints (==1.18.1) ; extra == 'doc'
Requires-Dist: sphinx-inline-tabs (==2022.1.2b11) ; extra == 'doc'
Requires-Dist: sphinxcontrib-spelling (==7.3.2) ; extra == 'doc'
Requires-Dist: ipython (==8.2.0) ; extra == 'doc'
Requires-Dist: myst-parser (==0.17.2) ; extra == 'doc'
Requires-Dist: sphinxcontrib.asciinema (==0.3.3) ; extra == 'doc'
Provides-Extra: stable
Requires-Dist: numpy (==1.21.6) ; extra == 'stable'
Requires-Dist: pandas (==1.3.5) ; extra == 'stable'
Requires-Dist: scikit-learn (==1.0.2) ; extra == 'stable'
Requires-Dist: scipy (==1.7.3) ; extra == 'stable'
Provides-Extra: test
Requires-Dist: pytest ; extra == 'test'
Requires-Dist: pytest-cov ; extra == 'test'
